{"errors":[],"warnings":[],"namedChunkGroups":{"app":{"chunks":[5,4,0,1],"assets":["webpack-runtime-ca33c226e9d572d3694f.js","webpack-runtime-ca33c226e9d572d3694f.js.map","styles.e976df7d403c500c3bec.css","styles-dec9e9c2176ef563c1c6.js","styles-dec9e9c2176ef563c1c6.js.map","commons-09d41c1b268f3d3d9dc0.js","commons-09d41c1b268f3d3d9dc0.js.map","app-65ff53a97072e9cb5d0f.js","app-65ff53a97072e9cb5d0f.js.map"],"children":{},"childAssets":{}},"component---src-pages-404-tsx":{"chunks":[0,2],"assets":["commons-09d41c1b268f3d3d9dc0.js","commons-09d41c1b268f3d3d9dc0.js.map","component---src-pages-404-tsx-0f646ec9265948c7c9b2.js","component---src-pages-404-tsx-0f646ec9265948c7c9b2.js.map"],"children":{},"childAssets":{}},"component---src-pages-index-tsx":{"chunks":[0,3],"assets":["commons-09d41c1b268f3d3d9dc0.js","commons-09d41c1b268f3d3d9dc0.js.map","component---src-pages-index-tsx-58574ac3b62233e3ecf6.js","component---src-pages-index-tsx-58574ac3b62233e3ecf6.js.map"],"children":{},"childAssets":{}}},"assetsByChunkName":{"app":["webpack-runtime-ca33c226e9d572d3694f.js","styles.e976df7d403c500c3bec.css","styles-dec9e9c2176ef563c1c6.js","commons-09d41c1b268f3d3d9dc0.js","app-65ff53a97072e9cb5d0f.js"],"component---src-pages-404-tsx":["commons-09d41c1b268f3d3d9dc0.js","component---src-pages-404-tsx-0f646ec9265948c7c9b2.js"],"component---src-pages-index-tsx":["commons-09d41c1b268f3d3d9dc0.js","component---src-pages-index-tsx-58574ac3b62233e3ecf6.js"]}}